ftdi_io-0.1.3.dist-info/licenses/LICENSE
ftio/__init__.py
ftio/_ft_define.py
ftio/ftio.py
ftdi_io-0.1.3.dist-info/METADATA
ftdi_io-0.1.3.dist-info/WHEEL
ftdi_io-0.1.3.dist-info/top_level.txt
ftdi_io-0.1.3.dist-info/RECORD
