Metadata-Version: 2.4
Name: ftdi-io
Version: 0.1.3
Summary: This is a simple program to control the FTDI chips IO pins.
Author-email: Dreamer <wby951@qq.com>
License-Expression: MIT
Project-URL: Homepage, https://github.com/DreamerDK/ftdi_io
Keywords: ftdi,ftd2xx,ftio,ftdiio
Requires-Python: >=3.8
License-File: LICENSE
Requires-Dist: ftd2xx>=1.3.8
Dynamic: license-file
